AUTHORS
ChangeLog
MANIFEST.in
README.rst
announce.rst
requirements.txt
setup.cfg
setup.py
tox.ini
linkscrubber/__init__.py
linkscrubber/main.py
linkscrubber.egg-info/PKG-INFO
linkscrubber.egg-info/SOURCES.txt
linkscrubber.egg-info/dependency_links.txt
linkscrubber.egg-info/entry_points.txt
linkscrubber.egg-info/not-zip-safe
linkscrubber.egg-info/requires.txt
linkscrubber.egg-info/top_level.txt
linkscrubber/cmd/__init__.py
linkscrubber/cmd/redirects.py
linkscrubber/cmd/sites.py
linkscrubber/cmd/tags.py
tests/test_get_bookmarks.py
tests/test_update_worker.py