Metadata-Version: 1.1
Name: linkscrubber
Version: 1.1.0
Summary: pinboard.in bookmark cleaner
Home-page: https://github.com/dhellmann/link_scrubber
Author: Doug Hellmann
Author-email: doug@doughellmann.com
License: UNKNOWN
Platform: UNKNOWN
Classifier: Development Status :: 5 - Production/Stable
Classifier: License :: OSI Approved :: MIT License
Classifier: Programming Language :: Python
Classifier: Programming Language :: Python :: 2
Classifier: Programming Language :: Python :: 2.7
Classifier: Programming Language :: Python :: 3
Classifier: Programming Language :: Python :: 3.3
Classifier: Environment :: Console
